<?xml version="1.0"?>
<!--
  Copyright (c) 2022, Oracle and/or its affiliates.

  Licensed under the Universal Permissive License v 1.0 as shown at
  https://oss.oracle.com/licenses/upl.
  -->

<cache-config xmlns:xsi="http://www.w3.org/2001/XMLSchema-instance"
              xmlns="http://xmlns.oracle.com/coherence/coherence-cache-config"
              xsi:schemaLocation="http://xmlns.oracle.com/coherence/coherence-cache-config coherence-cache-config.xsd"
              xml-override="{coherence.cacheconfig.override}">
  <defaults>
    <scope-name>${coherence.scope}</scope-name>
    <serializer>${coherence.serializer}</serializer>
  </defaults>

  <caching-scheme-mapping>
    <cache-mapping>
      <cache-name>*</cache-name>
      <scheme-name>grpc-fixed</scheme-name>
    </cache-mapping>
  </caching-scheme-mapping>

  <caching-schemes>
    <remote-grpc-cache-scheme>
      <scheme-name>grpc-fixed</scheme-name>
      <service-name>FixedRemoteGrpcCache</service-name>
      <grpc-channel>
        <remote-addresses>
          <socket-address>
            <address>127.0.0.1</address>
            <port>1408</port>
          </socket-address>
        </remote-addresses>
      </grpc-channel>
    </remote-grpc-cache-scheme>
  </caching-schemes>
</cache-config>
